FileQueryResult.py
JsonSchemaValidate.py
LlmServer.py
TaskMcpClient.py
ToMarkItDown.py
taskmcpclient-0.1.53.dist-info/METADATA
taskmcpclient-0.1.53.dist-info/WHEEL
taskmcpclient-0.1.53.dist-info/entry_points.txt
taskmcpclient-0.1.53.dist-info/top_level.txt
taskmcpclient-0.1.53.dist-info/RECORD
